{
  "come": {
    "ipa": "kʌm",
    "cn": "来"
  },
  "get": {
    "ipa": "ɡɛt",
    "cn": "得到"
  },
  "give": {
    "ipa": "ɡɪv",
    "cn": "给予"
  },
  "go": {
    "ipa": "ɡəʊ",
    "cn": "去"
  },
  "keep": {
    "ipa": "kiːp",
    "cn": "保持"
  },
  "let": {
    "ipa": "lɛt",
    "cn": "让"
  },
  "make": {
    "ipa": "meɪk",
    "cn": "制造"
  },
  "put": {
    "ipa": "pʊt",
    "cn": "放置"
  },
  "seem": {
    "ipa": "siːm",
    "cn": "似乎"
  },
  "take": {
    "ipa": "teɪk",
    "cn": "拿"
  },
  "do": {
    "ipa": "dʉː",
    "cn": "做"
  },
  "say": {
    "ipa": "seɪ",
    "cn": "说"
  },
  "see": {
    "ipa": "siː",
    "cn": "看见"
  },
  "send": {
    "ipa": "sɛnd",
    "cn": "发送"
  },
  "may": {
    "ipa": "meɪ",
    "cn": "可以"
  },
  "will": {
    "ipa": "wɪl",
    "cn": "将会"
  },
  "about": {
    "ipa": "əˈbɛʊt",
    "cn": "关于"
  },
  "across": {
    "ipa": "əˈkɹɑs",
    "cn": "横过"
  },
  "after": {
    "ipa": "ˈæf.tə(ɹ)",
    "cn": "之后"
  },
  "against": {
    "ipa": "əˈɡeɪnst",
    "cn": "对抗"
  },
  "among": {
    "ipa": "əˈmɒŋ",
    "cn": "在...中"
  },
  "before": {
    "ipa": "bɪˈfɔː",
    "cn": "之前"
  },
  "between": {
    "ipa": "bɪˈtwiːn",
    "cn": "在...之间"
  },
  "much": {
    "ipa": "mʌt͡ʃ",
    "cn": "很多"
  },
  "not": {
    "ipa": "nɒt",
    "cn": "不"
  },
  "only": {
    "ipa": "ˈəʊn.li",
    "cn": "只有"
  },
  "quite": {
    "ipa": "kwaɪt",
    "cn": "相当"
  },
  "so": {
    "ipa": "səʊ",
    "cn": "如此"
  },
  "very": {
    "ipa": "ˈvɛɹi",
    "cn": "非常"
  },
  "tomorrow": {
    "ipa": "təˈmɒɹəʊ",
    "cn": "明天"
  },
  "yesterday": {
    "ipa": "ˈjɛstədeɪ",
    "cn": "昨天"
  },
  "north": {
    "ipa": "nɔːθ",
    "cn": "北方"
  },
  "south": {
    "ipa": "saʊθ",
    "cn": "南方"
  },
  "east": {
    "ipa": "iːst",
    "cn": "东方"
  },
  "west": {
    "ipa": "wɛst",
    "cn": "西方"
  },
  "please": {
    "ipa": "pliːz",
    "cn": "请"
  },
  "yes": {
    "ipa": "jɛs",
    "cn": "是"
  },
  "account": {
    "ipa": "ə.ˈkaʊnt",
    "cn": "账户"
  },
  "act": {
    "ipa": "æk",
    "cn": "行为"
  },
  "addition": {
    "ipa": "æˈdɪʃən",
    "cn": "增加"
  },
  "adjustment": {
    "ipa": "əˈdʒʌst.mənt",
    "cn": "调整"
  },
  "advertisement": {
    "ipa": "ədˈvɜːtɪsmənt",
    "cn": "广告"
  },
  "agreement": {
    "ipa": "əˈɡɹiːmənt",
    "cn": "协议"
  },
  "air": {
    "ipa": "ˈɛə",
    "cn": "空气"
  },
  "amount": {
    "ipa": "əˈmaʊnt",
    "cn": "数量"
  },
  "amusement": {
    "ipa": "əˈmjuzmənt",
    "cn": "娱乐"
  },
  "animal": {
    "ipa": "ˈænɪməl",
    "cn": "动物"
  },
  "answer": {
    "ipa": "ˈan.sə",
    "cn": "回答"
  },
  "apparatus": {
    "ipa": "æpəˈɹɑːtəs",
    "cn": "设备"
  },
  "approval": {
    "ipa": "əˈpɹuːvəl",
    "cn": "批准"
  },
  "argument": {
    "ipa": "ˈɑːɡjʊmənt",
    "cn": "争论"
  },
  "art": {
    "ipa": "ɑːt",
    "cn": "艺术"
  },
  "attack": {
    "ipa": "əˈtæk",
    "cn": "攻击"
  },
  "day": {
    "ipa": "deɪ",
    "cn": "白天"
  },
  "death": {
    "ipa": "diːθ",
    "cn": "死亡"
  },
  "debt": {
    "ipa": "dɛt",
    "cn": "债务"
  },
  "decision": {
    "ipa": "dɪˈsɪʒən",
    "cn": "决定"
  },
  "degree": {
    "ipa": "dɪˈɡɹiː",
    "cn": "程度"
  },
  "design": {
    "ipa": "dɪˈzaɪn",
    "cn": "设计"
  },
  "desire": {
    "ipa": "dɪˈzaɪə",
    "cn": "欲望"
  },
  "destruction": {
    "ipa": "ˌdɪsˈtɹʌkʃən",
    "cn": "破坏"
  },
  "detail": {
    "ipa": "ˈdiːteɪl",
    "cn": "细节"
  },
  "development": {
    "ipa": "dɪˈvɛləpmənt",
    "cn": "发展"
  },
  "digestion": {
    "ipa": "daɪˈdʒɛstʃən",
    "cn": "消化"
  },
  "direction": {
    "ipa": "d(a)ɪˈɹɛk.ʃən",
    "cn": "方向"
  },
  "discovery": {
    "ipa": "dɪsˈkʌvəɹi",
    "cn": "发现"
  },
  "discussion": {
    "ipa": "dɪsˈkʊʃən",
    "cn": "讨论"
  },
  "disease": {
    "ipa": "dɪˈziːz",
    "cn": "疾病"
  },
  "disgust": {
    "ipa": "dɪsˈɡʌst",
    "cn": "厌恶"
  },
  "distance": {
    "ipa": "ˈdɪs.təns",
    "cn": "距离"
  },
  "distribution": {
    "ipa": "ˌdɪstɹəˈbjuːʃən",
    "cn": "分配"
  },
  "division": {
    "ipa": "dɪˈvɪʒən",
    "cn": "分配"
  },
  "doubt": {
    "ipa": "dʌʊt",
    "cn": "怀疑"
  },
  "drink": {
    "ipa": "dɹɪŋk",
    "cn": "喝"
  },
  "driving": {
    "ipa": "ˈdɹaɪvɪŋ",
    "cn": "驾驶"
  },
  "dust": {
    "ipa": "dʌst",
    "cn": "灰尘"
  },
  "earth": {
    "ipa": "ɜːθ",
    "cn": "地球"
  },
  "edge": {
    "ipa": "ɛdʒ",
    "cn": "边缘"
  },
  "education": {
    "ipa": "ˌɛdjʊˈkeɪʃn̩",
    "cn": "教育"
  },
  "effect": {
    "ipa": "ɪˈfɛkt",
    "cn": "影响"
  },
  "end": {
    "ipa": "ɛnd",
    "cn": "结尾"
  },
  "interest": {
    "ipa": "ˈɪntəɹɪst",
    "cn": "兴趣"
  },
  "invention": {
    "ipa": "ɪnˈvɛnʃən",
    "cn": "发明"
  },
  "iron": {
    "ipa": "ˈaɪən",
    "cn": "铁"
  },
  "jelly": {
    "ipa": "ˈd͡ʒɛl.i",
    "cn": "果冻"
  },
  "join": {
    "ipa": "ˈdʒɔɪn",
    "cn": "加入"
  },
  "journey": {
    "ipa": "ˈd͡ʒɜːni",
    "cn": "旅行"
  },
  "judge": {
    "ipa": "d͡ʒʌd͡ʒ",
    "cn": "法官"
  },
  "jump": {
    "ipa": "dʒʌmp",
    "cn": "跳"
  },
  "kick": {
    "ipa": "kɪk",
    "cn": "踢"
  },
  "kiss": {
    "ipa": "kɪs",
    "cn": "吻"
  },
  "knowledge": {
    "ipa": "ˈnɒlɪdʒ",
    "cn": "知识"
  },
  "land": {
    "ipa": "lænd",
    "cn": "土地"
  },
  "language": {
    "ipa": "ˈleɪŋɡwɪd͡ʒ",
    "cn": "语言"
  },
  "laugh": {
    "ipa": "lɑːf",
    "cn": "笑"
  },
  "law": {
    "ipa": "lɔː",
    "cn": "法律"
  },
  "lead": {
    "ipa": "lɛd",
    "cn": "带领"
  },
  "learning": {
    "ipa": "ˈlɜːnɪŋ",
    "cn": "学习"
  },
  "leather": {
    "ipa": "ˈlɛðə",
    "cn": "皮革"
  },
  "letter": {
    "ipa": "ˈlɛtə(ɹ)",
    "cn": "信"
  },
  "level": {
    "ipa": "ˈlɛv.əl",
    "cn": "等级"
  },
  "lift": {
    "ipa": "lɪft",
    "cn": "举起"
  },
  "light": {
    "ipa": "laɪt",
    "cn": "光"
  },
  "limit": {
    "ipa": "ˈlɪmt",
    "cn": "限制"
  },
  "linen": {
    "ipa": "ˈlɪnɪn",
    "cn": "亚麻布"
  },
  "play": {
    "ipa": "pleɪ",
    "cn": "玩"
  },
  "pleasure": {
    "ipa": "ˈplɛʒə",
    "cn": "乐趣"
  },
  "point": {
    "ipa": "pɔɪnt",
    "cn": "观点"
  },
  "poison": {
    "ipa": "ˈpɔɪz(ə)n",
    "cn": "毒"
  },
  "polish": {
    "ipa": "ˈpɒlɪʃ",
    "cn": "抛光"
  },
  "porter": {
    "ipa": "ˈpɔːtə",
    "cn": "搬运工"
  },
  "position": {
    "ipa": "pəˈzɪʃ(ə)n",
    "cn": "位置"
  },
  "powder": {
    "ipa": "ˈpaʊ.də(ɹ)",
    "cn": "粉末"
  },
  "power": {
    "ipa": "ˈpaʊ.ə(ɹ)",
    "cn": "力量"
  },
  "price": {
    "ipa": "pɹaɪs",
    "cn": "价格"
  },
  "print": {
    "ipa": "pɹɪnt",
    "cn": "打印"
  },
  "process": {
    "ipa": "ˈpɹəʊsɛs",
    "cn": "过程"
  },
  "produce": {
    "ipa": "pɹəˈdjuːs",
    "cn": "生产"
  },
  "profit": {
    "ipa": "ˈpɹɒfɪt",
    "cn": "利润"
  },
  "property": {
    "ipa": "ˈpɹɒp.ət.i",
    "cn": "财产"
  },
  "prose": {
    "ipa": "ˈpɹəʊz",
    "cn": "散文"
  },
  "protest": {
    "ipa": "ˈpɹəʊ.tɛst",
    "cn": "反对"
  },
  "pull": {
    "ipa": "pʊl",
    "cn": "拉"
  },
  "punishment": {
    "ipa": "ˈpʌnɪʃmənt",
    "cn": "惩罚"
  },
  "purpose": {
    "ipa": "ˈpɜːpəs",
    "cn": "目的"
  },
  "push": {
    "ipa": "pʷʊʃ",
    "cn": "推"
  },
  "quality": {
    "ipa": "ˈkwɒlɪti",
    "cn": "质量"
  },
  "question": {
    "ipa": "ˈkwɛstjən",
    "cn": "问题"
  },
  "rain": {
    "ipa": "ɹeɪn",
    "cn": "雨"
  },
  "range": {
    "ipa": "ɹeɪndʒ",
    "cn": "范围"
  },
  "rate": {
    "ipa": "ɹeɪt",
    "cn": "速度"
  },
  "ray": {
    "ipa": "ɹeɪ",
    "cn": "射线"
  },
  "reaction": {
    "ipa": "ɹiˈækʃən",
    "cn": "反应"
  },
  "reading": {
    "ipa": "ˈɹidiŋ",
    "cn": "阅读"
  },
  "reason": {
    "ipa": "ˈɹiːzən",
    "cn": "原因"
  },
  "record": {
    "ipa": "ˈɹɛkɔːd",
    "cn": "记录"
  },
  "steel": {
    "ipa": "stiːl",
    "cn": "钢"
  },
  "step": {
    "ipa": "stɛp",
    "cn": "步"
  },
  "stitch": {
    "ipa": "stɪt͡ʃ",
    "cn": "缝"
  },
  "stone": {
    "ipa": "stəʊn",
    "cn": "石头"
  },
  "stop": {
    "ipa": "stɒp",
    "cn": "停止"
  },
  "story": {
    "ipa": "ˈstɔː.ɹi",
    "cn": "故事"
  },
  "stretch": {
    "ipa": "stɹɛtʃ",
    "cn": "拉紧"
  },
  "structure": {
    "ipa": "ˈstɹʌktʃə(ɹ)",
    "cn": "结构"
  },
  "substance": {
    "ipa": "ˈsʌbstəns",
    "cn": "物质"
  },
  "sugar": {
    "ipa": "ˈʃʊɡə(ɹ)",
    "cn": "糖"
  },
  "suggestion": {
    "ipa": "səˈd͡ʒɛstjən",
    "cn": "建议"
  },
  "summer": {
    "ipa": "ˈsʌmə(ɹ)",
    "cn": "夏天"
  },
  "support": {
    "ipa": "səˈpɔːt",
    "cn": "支持"
  },
  "surprise": {
    "ipa": "səˈpɹaɪz",
    "cn": "惊喜"
  },
  "swim": {
    "ipa": "swɪm",
    "cn": "游泳"
  },
  "system": {
    "ipa": "ˈsɪstəm",
    "cn": "系统"
  },
  "talk": {
    "ipa": "toːk",
    "cn": "讲话"
  },
  "taste": {
    "ipa": "teɪst",
    "cn": "品尝"
  },
  "tax": {
    "ipa": "tæks",
    "cn": "税"
  },
  "teaching": {
    "ipa": "ˈtiːtʃɪŋ",
    "cn": "教学"
  },
  "tendency": {
    "ipa": "ˈtɛndənsi",
    "cn": "趋势"
  },
  "test": {
    "ipa": "test",
    "cn": "测试"
  },
  "theory": {
    "ipa": "ˈθiːəɹi",
    "cn": "理论"
  },
  "thing": {
    "ipa": "θɪŋ",
    "cn": "事物"
  },
  "thought": {
    "ipa": "θɔːt",
    "cn": "想法"
  },
  "thunder": {
    "ipa": "ˈθʌndə",
    "cn": "雷"
  },
  "time": {
    "ipa": "tɑem",
    "cn": "时间"
  },
  "tin": {
    "ipa": "tɪn",
    "cn": "锡"
  },
  "top": {
    "ipa": "tɒp",
    "cn": "顶部"
  },
  "trade": {
    "ipa": "tɹeɪd",
    "cn": "贸易"
  },
  "boot": {
    "ipa": "buːt",
    "cn": "启动"
  },
  "bottle": {
    "ipa": "ˈbɒ.təl",
    "cn": "瓶子"
  },
  "box": {
    "ipa": "bɒks",
    "cn": "盒子"
  },
  "boy": {
    "ipa": "bɔːə",
    "cn": "男孩"
  },
  "brain": {
    "ipa": "bɹeɪn",
    "cn": "脑"
  },
  "brake": {
    "ipa": "bɹeɪk",
    "cn": "制动"
  },
  "branch": {
    "ipa": "bɹɑːntʃ",
    "cn": "分支"
  },
  "brick": {
    "ipa": "bɹɪk",
    "cn": "砖"
  },
  "bridge": {
    "ipa": "bɹɪd͡ʒ",
    "cn": "桥"
  },
  "brush": {
    "ipa": "bɹʌʃ",
    "cn": "刷子"
  },
  "bucket": {
    "ipa": "ˈbʌkɪt",
    "cn": "桶"
  },
  "bulb": {
    "ipa": "bʌlb",
    "cn": "电灯泡"
  },
  "button": {
    "ipa": "ˈbʌtn̩",
    "cn": "按钮"
  },
  "cake": {
    "ipa": "keɪk",
    "cn": "蛋糕"
  },
  "camera": {
    "ipa": "ˈkæməɹə",
    "cn": "相机"
  },
  "card": {
    "ipa": "kɑːd",
    "cn": "卡片"
  },
  "cart": {
    "ipa": "kɑːt",
    "cn": "大车"
  },
  "carriage": {
    "ipa": "ˈkæɹɪdʒ",
    "cn": "运输"
  },
  "cat": {
    "ipa": "kat",
    "cn": "猫"
  },
  "chain": {
    "ipa": "ˈt͡ʃeɪn",
    "cn": "链"
  },
  "cheese": {
    "ipa": "t͡ʃiz",
    "cn": "奶酪"
  },
  "chest": {
    "ipa": "t͡ʃɛst",
    "cn": "胸部"
  },
  "chin": {
    "ipa": "tʃɪn",
    "cn": "下巴"
  },
  "church": {
    "ipa": "t͡ʃɜːt͡ʃ",
    "cn": "教堂"
  },
  "circle": {
    "ipa": "ˈsɜɹkəl",
    "cn": "圆圈"
  },
  "clock": {
    "ipa": "klɒk",
    "cn": "时钟"
  },
  "cloud": {
    "ipa": "klaʊd",
    "cn": "云"
  },
  "coat": {
    "ipa": "kəʊt",
    "cn": "外套"
  },
  "collar": {
    "ipa": "ˈkɒl.ə",
    "cn": "衣领"
  },
  "comb": {
    "ipa": "kəʊm",
    "cn": "梳子"
  },
  "cord": {
    "ipa": "kɔːd",
    "cn": "绳索"
  },
  "cow": {
    "ipa": "kaʊ",
    "cn": "母牛"
  },
  "cup": {
    "ipa": "kʌp",
    "cn": "杯子"
  },
  "curtain": {
    "ipa": "ˈkɜːtn̩",
    "cn": "窗帘"
  },
  "needle": {
    "ipa": "ˈniː.dl",
    "cn": "针"
  },
  "nerve": {
    "ipa": "nɛɾv",
    "cn": "神经"
  },
  "nose": {
    "ipa": "nəʊz",
    "cn": "鼻子"
  },
  "nut": {
    "ipa": "nɐt",
    "cn": "坚果"
  },
  "office": {
    "ipa": "ˈɑfɪs",
    "cn": "办公室"
  },
  "orange": {
    "ipa": "ˈɔɹɪ̈nd͡ʒ",
    "cn": "橙子"
  },
  "oven": {
    "ipa": "ˈʌ.vn̩",
    "cn": "烤箱"
  },
  "parcel": {
    "ipa": "ˈpʰaː.səɫ",
    "cn": "包裹"
  },
  "pen": {
    "ipa": "pɛn",
    "cn": "笔"
  },
  "pencil": {
    "ipa": "ˈpɛnsɪl",
    "cn": "铅笔"
  },
  "picture": {
    "ipa": "ˈpɪktʃə",
    "cn": "图片"
  },
  "pig": {
    "ipa": "ˈpɪɡ",
    "cn": "猪"
  },
  "pin": {
    "ipa": "pɪn",
    "cn": "别针"
  },
  "pipe": {
    "ipa": "paɪp",
    "cn": "管道"
  },
  "plane": {
    "ipa": "pleɪn",
    "cn": "飞机"
  },
  "plate": {
    "ipa": "pleɪt",
    "cn": "盘子"
  },
  "plough": {
    "ipa": "plaʊ",
    "cn": "犁"
  },
  "pocket": {
    "ipa": "ˈpɒkɪt",
    "cn": "口袋"
  },
  "pot": {
    "ipa": "pɒt",
    "cn": "锅"
  },
  "potato": {
    "ipa": "pəˈteɪ.təʊ",
    "cn": "土豆"
  },
  "prison": {
    "ipa": "ˈpɹɪzən",
    "cn": "监狱"
  },
  "pump": {
    "ipa": "pʌmp",
    "cn": "泵"
  },
  "rail": {
    "ipa": "ɹeɪl",
    "cn": "轨"
  },
  "rat": {
    "ipa": "ɹæt",
    "cn": "鼠"
  },
  "receipt": {
    "ipa": "ɹɪˈsiːt",
    "cn": "收据"
  },
  "ring": {
    "ipa": "ɹɪŋ",
    "cn": "戒指"
  },
  "rod": {
    "ipa": "ɹɒd",
    "cn": "杆"
  },
  "roof": {
    "ipa": "ɹuːf",
    "cn": "屋顶"
  },
  "root": {
    "ipa": "ɹuːt",
    "cn": "根"
  },
  "sail": {
    "ipa": "seɪl",
    "cn": "帆"
  },
  "school": {
    "ipa": "skuːl",
    "cn": "学校"
  },
  "scissors": {
    "ipa": "ˈsɪzəz",
    "cn": "剪刀"
  },
  "screw": {
    "ipa": "skɹuː",
    "cn": "拧紧"
  },
  "seed": {
    "ipa": "siːd",
    "cn": "种子"
  },
  "sheep": {
    "ipa": "ʃiːp",
    "cn": "羊"
  },
  "shelf": {
    "ipa": "ʃɛlf",
    "cn": "架子"
  },
  "ship": {
    "ipa": "ʃɪp",
    "cn": "船"
  },
  "shirt": {
    "ipa": "ʃɜːt",
    "cn": "衬衫"
  },
  "shoe": {
    "ipa": "ʃuː",
    "cn": "鞋"
  },
  "skin": {
    "ipa": "skɪn",
    "cn": "皮肤"
  },
  "skirt": {
    "ipa": "skɜːt",
    "cn": "裙子"
  },
  "snake": {
    "ipa": "ˈsneɪk",
    "cn": "蛇"
  },
  "elastic": {
    "ipa": "iˈlæstɪk",
    "cn": "有弹性的"
  },
  "electric": {
    "ipa": "əˈlɛktɹɪk",
    "cn": "电的"
  },
  "equal": {
    "ipa": "ˈiːkwəl",
    "cn": "相等的"
  },
  "fat": {
    "ipa": "fæt",
    "cn": "肥胖的"
  },
  "fertile": {
    "ipa": "ˈfɝːtaɪl",
    "cn": "肥沃的"
  },
  "first": {
    "ipa": "fɪrst",
    "cn": "第一的"
  },
  "fixed": {
    "ipa": "fɪkst",
    "cn": "固定的"
  },
  "flat": {
    "ipa": "flæt",
    "cn": "平的"
  },
  "free": {
    "ipa": "fɹiː",
    "cn": "自由的"
  },
  "frequent": {
    "ipa": "ˈfɹiː.kwənt",
    "cn": "频繁的"
  },
  "full": {
    "ipa": "fʊl",
    "cn": "满的"
  },
  "general": {
    "ipa": "ˈd͡ʒɛnɹəl",
    "cn": "一般的"
  },
  "good": {
    "ipa": "ɡʊ(d)",
    "cn": "好的"
  },
  "great": {
    "ipa": "ɡɹeɪt",
    "cn": "伟大的"
  },
  "grey": {
    "ipa": "ɡɹeɪ",
    "cn": "灰色的"
  },
  "hanging": {
    "ipa": "ˈhæŋɪŋ",
    "cn": "悬挂的"
  },
  "happy": {
    "ipa": "ˈhæpiː",
    "cn": "快乐的"
  },
  "hard": {
    "ipa": "hɑːd",
    "cn": "困难的"
  },
  "healthy": {
    "ipa": "ˈhɛl.θi",
    "cn": "健康的"
  },
  "high": {
    "ipa": "haɪ",
    "cn": "高的"
  },
  "hollow": {
    "ipa": "ˈhɒl.əʊ",
    "cn": "中空的"
  },
  "important": {
    "ipa": "ɪmˈpɔːtənt",
    "cn": "重要的"
  },
  "kind": {
    "ipa": "kaɪnd",
    "cn": "亲切的"
  },
  "like": {
    "ipa": "laɪk",
    "cn": "喜欢的"
  },
  "living": {
    "ipa": "ˈlɪvɪŋ",
    "cn": "活的"
  },
  "long": {
    "ipa": "ˈlɔːŋ",
    "cn": "长的"
  },
  "male": {
    "ipa": "meɪl",
    "cn": "男性的"
  },
  "married": {
    "ipa": "ˈmæɹ.ɪd",
    "cn": "已婚的"
  },
  "material": {
    "ipa": "məˈtɪəɹɪəl",
    "cn": "材料的"
  },
  "medical": {
    "ipa": "ˈmɛdɪkl̩",
    "cn": "医学的"
  },
  "military": {
    "ipa": "ˈmɪl.ɪ.tɹi",
    "cn": "军事的"
  },
  "natural": {
    "ipa": "ˈnætʃəɹəl",
    "cn": "自然的"
  },
  "necessary": {
    "ipa": "ˈnɛsəsɹɪ",
    "cn": "必要的"
  },
  "new": {
    "ipa": "njuː",
    "cn": "新的"
  },
  "normal": {
    "ipa": "ˈnɔːməl",
    "cn": "正常的"
  },
  "open": {
    "ipa": "ˈəʊ.pən",
    "cn": "开放的"
  },
  "parallel": {
    "ipa": "ˈpæɹəˌlɛl",
    "cn": "平行线"
  },
  "past": {
    "ipa": "pɑːst",
    "cn": "过去的"
  },
  "physical": {
    "ipa": "ˈfɪzɪkəl",
    "cn": "物理的"
  },
  "political": {
    "ipa": "pəˈlɪtɪkəl",
    "cn": "政治的"
  },
  "poor": {
    "ipa": "pɔː(ɹ)",
    "cn": "贫穷的"
  },
  "possible": {
    "ipa": "ˈpɒsɪbl̩",
    "cn": "可能的"
  },
  "present": {
    "ipa": "pɹəˈzɛnt",
    "cn": "现在的"
  },
  "private": {
    "ipa": "ˈpɹaɪvət",
    "cn": "私人的"
  },
  "probable": {
    "ipa": "ˈpɹɒbəbl̩",
    "cn": "可能的"
  },
  "quick": {
    "ipa": "kwɪk",
    "cn": "快的"
  },
  "narrow": {
    "ipa": "ˈnæɹəʊ",
    "cn": "狭窄的"
  },
  "old": {
    "ipa": "ˈɒʊld",
    "cn": "老的"
  },
  "opposite": {
    "ipa": "ˈɒpəsɪt",
    "cn": "相反的"
  },
  "public": {
    "ipa": "ˈpʌblɪk",
    "cn": "公众的"
  },
  "rough": {
    "ipa": "ɹʌf",
    "cn": "粗糙的"
  },
  "sad": {
    "ipa": "sæd",
    "cn": "悲伤的"
  },
  "safe": {
    "ipa": "seɪf",
    "cn": "安全的"
  },
  "secret": {
    "ipa": "ˈsiːkɹət",
    "cn": "秘密的"
  },
  "short": {
    "ipa": "ʃɔːt",
    "cn": "短的"
  },
  "shut": {
    "ipa": "ʃʌt",
    "cn": "关闭"
  },
  "simple": {
    "ipa": "ˈsɪmpəl",
    "cn": "简单的"
  },
  "slow": {
    "ipa": "sləʊ",
    "cn": "慢的"
  },
  "small": {
    "ipa": "smɔːl",
    "cn": "小的"
  },
  "soft": {
    "ipa": "sɒft",
    "cn": "柔软的"
  },
  "solid": {
    "ipa": "ˈsɒlɪd",
    "cn": "坚硬的"
  },
  "special": {
    "ipa": "ˈspɛ.ʃəl",
    "cn": "特别的"
  },
  "strange": {
    "ipa": "ˈstɹeɪnd͡ʒ",
    "cn": "奇怪的"
  },
  "thin": {
    "ipa": "ˈθɪn",
    "cn": "薄的"
  },
  "white": {
    "ipa": "waɪt",
    "cn": "白色的"
  },
  "wrong": {
    "ipa": "ɹɒŋ",
    "cn": "错误的"
  },
  "by": {
    "ipa": "baɪ",
    "cn": "通过"
  },
  "down": {
    "ipa": "daʊn",
    "cn": "下"
  },
  "from": {
    "ipa": "fɹɒm",
    "cn": "来自"
  },
  "in": {
    "ipa": "ɪn",
    "cn": "在"
  },
  "off": {
    "ipa": "ɒf",
    "cn": "关闭"
  },
  "on": {
    "ipa": "ɒn",
    "cn": "开启"
  },
  "over": {
    "ipa": "ˈəʊ.və(ɹ)",
    "cn": "在...上"
  },
  "through": {
    "ipa": "θɹuː",
    "cn": "通过"
  },
  "to": {
    "ipa": "tʉː",
    "cn": "到"
  },
  "under": {
    "ipa": "ˈʊndə",
    "cn": "在...下"
  },
  "up": {
    "ipa": "ap",
    "cn": "上"
  },
  "of": {
    "ipa": "ɒv",
    "cn": "的"
  },
  "till": {
    "ipa": "tɪl",
    "cn": "直到"
  },
  "than": {
    "ipa": "ðæn",
    "cn": "比"
  },
  "a": {
    "ipa": "æɪ",
    "cn": "一个"
  },
  "the": {
    "ipa": "ði",
    "cn": "这个"
  },
  "all": {
    "ipa": "ɔːl",
    "cn": "所有"
  },
  "any": {
    "ipa": "ˈæni",
    "cn": "任何"
  },
  "no": {
    "ipa": "nəʊ",
    "cn": "没有"
  },
  "other": {
    "ipa": "ʊðə",
    "cn": "其他"
  },
  "some": {
    "ipa": "sɐm",
    "cn": "一些"
  },
  "such": {
    "ipa": "sʌt͡ʃ",
    "cn": "这样的"
  },
  "that": {
    "ipa": "ˈðæt",
    "cn": "那"
  },
  "this": {
    "ipa": "ðəs",
    "cn": "这"
  },
  "even": {
    "ipa": "ˈiːvən",
    "cn": "甚至"
  },
  "little": {
    "ipa": "ˈlɪtəl",
    "cn": "少许"
  },
  "attempt": {
    "ipa": "əˈtɛmpt",
    "cn": "试图"
  },
  "attention": {
    "ipa": "əˈtɛn.ʃən",
    "cn": "注意"
  },
  "attraction": {
    "ipa": "əˈtɹækʃən",
    "cn": "景点"
  },
  "authority": {
    "ipa": "ɔːˈθɒɹəti",
    "cn": "权威"
  },
  "back": {
    "ipa": "bæk",
    "cn": "背部"
  },
  "balance": {
    "ipa": "ˈbæləns",
    "cn": "平衡"
  },
  "base": {
    "ipa": "beɪs",
    "cn": "根据"
  },
  "behaviour": {
    "ipa": "bɪˈheɪvjə",
    "cn": "行为"
  },
  "belief": {
    "ipa": "bəˈliːf",
    "cn": "信仰"
  },
  "birth": {
    "ipa": "bɜːθ",
    "cn": "出生"
  },
  "bit": {
    "ipa": "bɪt",
    "cn": "少量"
  },
  "bite": {
    "ipa": "bʌɪt",
    "cn": "咬"
  },
  "blood": {
    "ipa": "blʌd",
    "cn": "血"
  },
  "blow": {
    "ipa": "bləʊ",
    "cn": "吹"
  },
  "body": {
    "ipa": "ˈbɒdi",
    "cn": "身体"
  },
  "brass": {
    "ipa": "bɹɑːs",
    "cn": "黄铜"
  },
  "bread": {
    "ipa": "bɹɛd",
    "cn": "面包"
  },
  "breath": {
    "ipa": "bɹɛθ",
    "cn": "气息"
  },
  "brother": {
    "ipa": "ˈbɹʌðə(ɹ)",
    "cn": "兄弟"
  },
  "building": {
    "ipa": "ˈbɪl.dɪŋ",
    "cn": "建筑"
  },
  "burn": {
    "ipa": "bɜːn",
    "cn": "烧伤"
  },
  "burst": {
    "ipa": "bɜːst",
    "cn": "爆裂"
  },
  "business": {
    "ipa": "ˈbɪd.nəs",
    "cn": "生意"
  },
  "butter": {
    "ipa": "ˈbʊtə",
    "cn": "黄油"
  },
  "canvas": {
    "ipa": "ˈkæn.vəs",
    "cn": "帆布"
  },
  "care": {
    "ipa": "kɛə",
    "cn": "关心"
  },
  "cause": {
    "ipa": "kɔːz",
    "cn": "原因"
  },
  "chalk": {
    "ipa": "t͡ʃɔːk",
    "cn": "粉笔"
  },
  "chance": {
    "ipa": "tʃʰɑːns",
    "cn": "机会"
  },
  "change": {
    "ipa": "tʃeɪndʒ",
    "cn": "改变"
  },
  "event": {
    "ipa": "əˈvɛnt",
    "cn": "事件"
  },
  "example": {
    "ipa": "ɪɡˈzɑːmpl̩",
    "cn": "例子"
  },
  "exchange": {
    "ipa": "ɛksˈtʃeɪndʒ",
    "cn": "交换"
  },
  "existence": {
    "ipa": "ɛɡ.ˈzɪs.təns",
    "cn": "存在"
  },
  "expansion": {
    "ipa": "ɪkˈspænʃən",
    "cn": "扩张"
  },
  "experience": {
    "ipa": "ɪkˈspɪə.ɹɪəns",
    "cn": "经验"
  },
  "expert": {
    "ipa": "ˈɛkspəːt",
    "cn": "专家"
  },
  "fact": {
    "ipa": "fækt",
    "cn": "事实"
  },
  "fall": {
    "ipa": "fɔːl",
    "cn": "落下"
  },
  "family": {
    "ipa": "ˈfæm(ɪ)li",
    "cn": "家庭"
  },
  "father": {
    "ipa": "ˈfɑːðə(ɹ)",
    "cn": "父亲"
  },
  "fear": {
    "ipa": "fɪə",
    "cn": "害怕"
  },
  "feeling": {
    "ipa": "ˈfiːlɪŋ",
    "cn": "感觉"
  },
  "fiction": {
    "ipa": "ˈfɪk.ʃən",
    "cn": "小说"
  },
  "field": {
    "ipa": "fiːld",
    "cn": "场地"
  },
  "fight": {
    "ipa": "faɪt",
    "cn": "斗争"
  },
  "fire": {
    "ipa": "ˈfaɪə(ɹ)",
    "cn": "火"
  },
  "flame": {
    "ipa": "fleɪm",
    "cn": "火焰"
  },
  "flight": {
    "ipa": "flaɪt",
    "cn": "航班"
  },
  "flower": {
    "ipa": "ˈflaʊ.ə",
    "cn": "花"
  },
  "fold": {
    "ipa": "fəʊld",
    "cn": "折叠"
  },
  "food": {
    "ipa": "fuːd",
    "cn": "食物"
  },
  "force": {
    "ipa": "fɔːs",
    "cn": "力量"
  },
  "form": {
    "ipa": "fɔːm",
    "cn": "形式"
  },
  "friend": {
    "ipa": "fɹɛnd",
    "cn": "朋友"
  },
  "front": {
    "ipa": "fɹʌnt",
    "cn": "正面"
  },
  "fruit": {
    "ipa": "fɹuːt",
    "cn": "水果"
  },
  "glass": {
    "ipa": "ɡlɑːs",
    "cn": "玻璃"
  },
  "gold": {
    "ipa": "ɡɒʊld",
    "cn": "金子"
  },
  "government": {
    "ipa": "ˈɡʌvə(n)mənt",
    "cn": "政府"
  },
  "grain": {
    "ipa": "ɡɹeɪn",
    "cn": "粮食"
  },
  "grass": {
    "ipa": "ɡɹ̠ɑːs",
    "cn": "草"
  },
  "grip": {
    "ipa": "ɡɹɪp",
    "cn": "紧握"
  },
  "group": {
    "ipa": "ɡɹuːp",
    "cn": "团体"
  },
  "growth": {
    "ipa": "ɡɹəʊθ",
    "cn": "生长"
  },
  "guide": {
    "ipa": "ɡaɪd",
    "cn": "指导"
  },
  "harbour": {
    "ipa": "ˈhɑːbə",
    "cn": "港口"
  },
  "harmony": {
    "ipa": "ˈhɑːməni",
    "cn": "和谐"
  },
  "hate": {
    "ipa": "heɪt",
    "cn": "恨"
  },
  "hearing": {
    "ipa": "ˈhɪəɹ.ɪŋ",
    "cn": "听力"
  },
  "heat": {
    "ipa": "hit",
    "cn": "热"
  },
  "help": {
    "ipa": "hɛlp",
    "cn": "帮助"
  },
  "history": {
    "ipa": "ˈhɪst(ə)ɹi",
    "cn": "历史"
  },
  "hole": {
    "ipa": "həʊl",
    "cn": "洞"
  },
  "hope": {
    "ipa": "həʊp",
    "cn": "希望"
  },
  "hour": {
    "ipa": "ˈaʊə(ɹ)",
    "cn": "小时"
  },
  "humour": {
    "ipa": "ˈhjuː.mə(ɹ)",
    "cn": "幽默"
  },
  "ice": {
    "ipa": "ʌɪs",
    "cn": "冰"
  },
  "idea": {
    "ipa": "aɪˈdɪə",
    "cn": "主意"
  },
  "impulse": {
    "ipa": "ˈɪmpʌls",
    "cn": "冲动"
  },
  "industry": {
    "ipa": "ˈɪndəstɹi",
    "cn": "行业"
  },
  "ink": {
    "ipa": "ɪŋk",
    "cn": "墨水"
  },
  "insect": {
    "ipa": "ˈɪnsɛkt",
    "cn": "昆虫"
  },
  "instrument": {
    "ipa": "ˈɪnstɹəmənt",
    "cn": "乐器"
  },
  "insurance": {
    "ipa": "ɪn.ˈʃɔː.ɹəns",
    "cn": "保险"
  },
  "liquid": {
    "ipa": "ˈlɪkwɪd",
    "cn": "液体"
  },
  "list": {
    "ipa": "lɪst",
    "cn": "列表"
  },
  "loss": {
    "ipa": "lɒs",
    "cn": "损失"
  },
  "love": {
    "ipa": "lʌv",
    "cn": "爱"
  },
  "machine": {
    "ipa": "məˈʃin",
    "cn": "机器"
  },
  "man": {
    "ipa": "mæn",
    "cn": "男人"
  },
  "manager": {
    "ipa": "ˈmæn.ɪ.dʒə",
    "cn": "经理"
  },
  "mark": {
    "ipa": "mɑɹk",
    "cn": "标记"
  },
  "market": {
    "ipa": "ˈmɑːkɪt",
    "cn": "市场"
  },
  "mass": {
    "ipa": "mæs",
    "cn": "大量的"
  },
  "meal": {
    "ipa": "miːl",
    "cn": "一顿饭"
  },
  "measure": {
    "ipa": "ˈmɛʒə",
    "cn": "措施"
  },
  "meat": {
    "ipa": "miːt",
    "cn": "肉"
  },
  "order": {
    "ipa": "ˈɔːdə",
    "cn": "命令"
  },
  "organization": {
    "ipa": "ˌɔɹɡənaɪˈzeɪʃən",
    "cn": "组织"
  },
  "ornament": {
    "ipa": "ˈɔː(ɹ)nəmənt",
    "cn": "装饰品"
  },
  "owner": {
    "ipa": "ˈəʊnə",
    "cn": "所有者"
  },
  "page": {
    "ipa": "peɪd͡ʒ",
    "cn": "页"
  },
  "pain": {
    "ipa": "peɪn",
    "cn": "疼痛"
  },
  "paint": {
    "ipa": "peɪnt",
    "cn": "画"
  },
  "paper": {
    "ipa": "ˈpeɪpə",
    "cn": "纸"
  },
  "part": {
    "ipa": "pɑːt",
    "cn": "部分"
  },
  "paste": {
    "ipa": "peɪst",
    "cn": "粘贴"
  },
  "payment": {
    "ipa": "ˈpeɪmənt",
    "cn": "支付"
  },
  "peace": {
    "ipa": "piːs",
    "cn": "和平"
  },
  "person": {
    "ipa": "ˈpɜːsən",
    "cn": "人"
  },
  "place": {
    "ipa": "pleɪs",
    "cn": "地方"
  },
  "plant": {
    "ipa": "plɑːnt",
    "cn": "植物"
  },
  "regret": {
    "ipa": "ɹiˈɡɹɛt",
    "cn": "后悔"
  },
  "relation": {
    "ipa": "ɹɪˈleɪʃən",
    "cn": "关系"
  },
  "religion": {
    "ipa": "ɹɪˈlɪdʒən",
    "cn": "宗教"
  },
  "representative": {
    "ipa": "ˌɹɛpɹɪˈzɛnt(ət)ɪv",
    "cn": "代表"
  },
  "request": {
    "ipa": "ɹɪˈkwɛst",
    "cn": "要求"
  },
  "respect": {
    "ipa": "ɹɪˈspɛkt",
    "cn": "尊重"
  },
  "rest": {
    "ipa": "ɹɛst",
    "cn": "休息"
  },
  "reward": {
    "ipa": "ɹəˈwɔːd",
    "cn": "报酬"
  },
  "rhythm": {
    "ipa": "ˈɹɪ.ð(ə)m",
    "cn": "韵律"
  },
  "rice": {
    "ipa": "ɹaɪs",
    "cn": "米"
  },
  "river": {
    "ipa": "ˈɹɪvə",
    "cn": "河"
  },
  "road": {
    "ipa": "ɹəʊd",
    "cn": "路"
  },
  "roll": {
    "ipa": "ɹəʊl",
    "cn": "卷"
  },
  "room": {
    "ipa": "ɹuːm",
    "cn": "房间"
  },
  "rub": {
    "ipa": "ɹʌb",
    "cn": "擦"
  },
  "rule": {
    "ipa": "ɹuːl",
    "cn": "规则"
  },
  "run": {
    "ipa": "ɹʊn",
    "cn": "跑步"
  },
  "salt": {
    "ipa": "sɒlt",
    "cn": "盐"
  },
  "sand": {
    "ipa": "sænd",
    "cn": "沙"
  },
  "soap": {
    "ipa": "səʊp",
    "cn": "肥皂"
  },
  "society": {
    "ipa": "səˈsaɪ.ə.ti",
    "cn": "社会"
  },
  "son": {
    "ipa": "sɒn",
    "cn": "儿子"
  },
  "song": {
    "ipa": "sɒŋ",
    "cn": "歌曲"
  },
  "sort": {
    "ipa": "sɔːt",
    "cn": "种类"
  },
  "sound": {
    "ipa": "saʊnd",
    "cn": "声音"
  },
  "soup": {
    "ipa": "suːp",
    "cn": "汤"
  },
  "space": {
    "ipa": "speɪs",
    "cn": "空间"
  },
  "stage": {
    "ipa": "steɪd͡ʒ",
    "cn": "阶段"
  },
  "start": {
    "ipa": "stɑːt",
    "cn": "开始"
  },
  "statement": {
    "ipa": "ˈsteɪtm(ə)nt",
    "cn": "陈述"
  },
  "steam": {
    "ipa": "stiːm",
    "cn": "蒸汽"
  },
  "trick": {
    "ipa": "tɹɪk",
    "cn": "诡计"
  },
  "trouble": {
    "ipa": "ˈtɹʌb(ə)l",
    "cn": "麻烦"
  },
  "turn": {
    "ipa": "tɜːn",
    "cn": "转动"
  },
  "twist": {
    "ipa": "twɪst",
    "cn": "捻"
  },
  "unit": {
    "ipa": "ˈjuː.nɪt",
    "cn": "单元"
  },
  "value": {
    "ipa": "ˈvæljuː",
    "cn": "价值"
  },
  "verse": {
    "ipa": "ˈvɜːs",
    "cn": "诗"
  },
  "vessel": {
    "ipa": "ˈvɛs.l̩",
    "cn": "血管"
  },
  "view": {
    "ipa": "vjuː",
    "cn": "看法"
  },
  "voice": {
    "ipa": "vɔɪs",
    "cn": "嗓音"
  },
  "walk": {
    "ipa": "wɔːk",
    "cn": "走"
  },
  "war": {
    "ipa": "wɔː",
    "cn": "战争"
  },
  "wash": {
    "ipa": "wɒʃ",
    "cn": "洗"
  },
  "waste": {
    "ipa": "weɪst",
    "cn": "浪费"
  },
  "water": {
    "ipa": "ˈwɔːtə",
    "cn": "水"
  },
  "wave": {
    "ipa": "weɪv",
    "cn": "海浪"
  },
  "wax": {
    "ipa": "wæks",
    "cn": "蜡"
  },
  "way": {
    "ipa": "weɪ",
    "cn": "方式"
  },
  "weather": {
    "ipa": "ˈwɛðə",
    "cn": "天气"
  },
  "week": {
    "ipa": "wiːk",
    "cn": "星期"
  },
  "weight": {
    "ipa": "weɪt",
    "cn": "重量"
  },
  "wind": {
    "ipa": "ˈwaɪnd",
    "cn": "风"
  },
  "wine": {
    "ipa": "waɪn",
    "cn": "葡萄酒"
  },
  "winter": {
    "ipa": "ˈwɪntɚ",
    "cn": "冬天"
  },
  "woman": {
    "ipa": "ˈwʊmən",
    "cn": "女士"
  },
  "wood": {
    "ipa": "wʊd",
    "cn": "木头"
  },
  "wool": {
    "ipa": "wʊl",
    "cn": "羊毛"
  },
  "word": {
    "ipa": "wɜːd",
    "cn": "单词"
  },
  "work": {
    "ipa": "wɜːk",
    "cn": "工作"
  },
  "wound": {
    "ipa": "wuːnd",
    "cn": "伤口"
  },
  "writing": {
    "ipa": "ˈɹaɪtɪŋ",
    "cn": "写作"
  },
  "year": {
    "ipa": "jɪə",
    "cn": "年"
  },
  "angle": {
    "ipa": "ˈæŋ.ɡəl",
    "cn": "角度"
  },
  "ant": {
    "ipa": "ɑːnt",
    "cn": "蚂蚁"
  },
  "apple": {
    "ipa": "ˈæp.əl",
    "cn": "苹果"
  },
  "arch": {
    "ipa": "ɑːt͡ʃ",
    "cn": "拱"
  },
  "arm": {
    "ipa": "ɑːm",
    "cn": "手臂"
  },
  "feather": {
    "ipa": "ˈfɛð.ə(ɹ)",
    "cn": "羽毛"
  },
  "finger": {
    "ipa": "ˈfɪŋəɹ",
    "cn": "手指"
  },
  "fish": {
    "ipa": "fɪʃ",
    "cn": "鱼"
  },
  "flag": {
    "ipa": "flæɡ",
    "cn": "旗帜"
  },
  "floor": {
    "ipa": "flɔː",
    "cn": "地面"
  },
  "fly": {
    "ipa": "flaɪ",
    "cn": "飞"
  },
  "foot": {
    "ipa": "fɵʔt",
    "cn": "脚"
  },
  "fork": {
    "ipa": "fɔːk",
    "cn": "叉"
  },
  "fowl": {
    "ipa": "faʊl",
    "cn": "鸡"
  },
  "frame": {
    "ipa": "fɹeɪm",
    "cn": "框架"
  },
  "garden": {
    "ipa": "ˈɡɑːdn̩",
    "cn": "花园"
  },
  "girl": {
    "ipa": "ɡɵːl",
    "cn": "女孩"
  },
  "glove": {
    "ipa": "ɡlʌv",
    "cn": "手套"
  },
  "goat": {
    "ipa": "ɡɐ̟ʉt",
    "cn": "山羊"
  },
  "gun": {
    "ipa": "ɡʌn",
    "cn": "枪"
  },
  "hair": {
    "ipa": "hɛə",
    "cn": "头发"
  },
  "hammer": {
    "ipa": "ˈhæm.ə(ɹ)",
    "cn": "锤"
  },
  "hand": {
    "ipa": "hænd",
    "cn": "手"
  },
  "hat": {
    "ipa": "hat",
    "cn": "帽子"
  },
  "head": {
    "ipa": "hɛd",
    "cn": "头"
  },
  "heart": {
    "ipa": "hɑːt",
    "cn": "心"
  },
  "hook": {
    "ipa": "huːk",
    "cn": "钩"
  },
  "horn": {
    "ipa": "hɔːn",
    "cn": "喇叭"
  },
  "horse": {
    "ipa": "hɔːs",
    "cn": "马"
  },
  "hospital": {
    "ipa": "ˈhɒs.pɪ.tl̩",
    "cn": "医院"
  },
  "house": {
    "ipa": "haʊs",
    "cn": "房子"
  },
  "island": {
    "ipa": "ˈaɪ̯lənd",
    "cn": "岛"
  },
  "jewel": {
    "ipa": "dʒul",
    "cn": "宝石"
  },
  "kettle": {
    "ipa": "ˈkɛ.təl",
    "cn": "壶"
  },
  "key": {
    "ipa": "kiː",
    "cn": "钥匙"
  },
  "knee": {
    "ipa": "niː",
    "cn": "膝盖"
  },
  "street": {
    "ipa": "stɹiːt",
    "cn": "街道"
  },
  "sun": {
    "ipa": "sʌn",
    "cn": "太阳"
  },
  "table": {
    "ipa": "ˈteɪbəl",
    "cn": "桌子"
  },
  "tail": {
    "ipa": "teɪl",
    "cn": "尾巴"
  },
  "thread": {
    "ipa": "θɾ̪̊ɛd",
    "cn": "线"
  },
  "throat": {
    "ipa": "ˈθɹəʊt",
    "cn": "喉"
  },
  "thumb": {
    "ipa": "θʌm",
    "cn": "拇指"
  },
  "ticket": {
    "ipa": "ˈtɪkɪt",
    "cn": "票"
  },
  "toe": {
    "ipa": "təʊ",
    "cn": "脚趾"
  },
  "tongue": {
    "ipa": "tɒŋɡ",
    "cn": "舌头"
  },
  "tooth": {
    "ipa": "tuːθ",
    "cn": "齿"
  },
  "town": {
    "ipa": "taʊn",
    "cn": "镇"
  },
  "train": {
    "ipa": "tɹeɪn",
    "cn": "火车"
  },
  "tray": {
    "ipa": "tɹeɪ",
    "cn": "托盘"
  },
  "tree": {
    "ipa": "tɹiː",
    "cn": "树"
  },
  "trousers": {
    "ipa": "ˈtɹaʊzəz",
    "cn": "裤子"
  },
  "umbrella": {
    "ipa": "ʌmˈbɹɛlə",
    "cn": "伞"
  },
  "wall": {
    "ipa": "wɔːl",
    "cn": "墙"
  },
  "watch": {
    "ipa": "wɒt͡ʃ",
    "cn": "手表"
  },
  "wheel": {
    "ipa": "ʍiːl",
    "cn": "车轮"
  },
  "whip": {
    "ipa": "wɪp",
    "cn": "鞭"
  },
  "whistle": {
    "ipa": "wɪsl̩",
    "cn": "哨"
  },
  "window": {
    "ipa": "ˈwɪndəʊ",
    "cn": "窗户"
  },
  "wing": {
    "ipa": "wɪŋ",
    "cn": "翼"
  },
  "wire": {
    "ipa": "waɪə(ɹ)",
    "cn": "金属丝"
  },
  "worm": {
    "ipa": "wɜːm",
    "cn": "蠕虫"
  },
  "able": {
    "ipa": "ˈeɪ.bl̩",
    "cn": "能够的"
  },
  "acid": {
    "ipa": "ˈæs.ɪd",
    "cn": "酸的"
  },
  "sharp": {
    "ipa": "ʃɑːp",
    "cn": "锋利的"
  },
  "smooth": {
    "ipa": "smuːð",
    "cn": "光滑的"
  },
  "sticky": {
    "ipa": "ˈstɪki",
    "cn": "黏的"
  },
  "stiff": {
    "ipa": "stɪf",
    "cn": "僵硬的"
  },
  "straight": {
    "ipa": "stɹeɪt",
    "cn": "直的"
  },
  "strong": {
    "ipa": "stɹɒŋ",
    "cn": "强壮的"
  },
  "sudden": {
    "ipa": "ˈsʌdən",
    "cn": "突然的"
  },
  "sweet": {
    "ipa": "swiːt",
    "cn": "甜的"
  },
  "tall": {
    "ipa": "tɔːl",
    "cn": "高的"
  },
  "thick": {
    "ipa": "θɪk",
    "cn": "厚的"
  },
  "tired": {
    "ipa": "taɪəd",
    "cn": "疲倦的"
  },
  "true": {
    "ipa": "tɹuː",
    "cn": "真实的"
  },
  "violent": {
    "ipa": "ˈvaɪ(ə)lənt",
    "cn": "暴力的"
  },
  "waiting": {
    "ipa": "ˈweɪ̯ɾɪŋ",
    "cn": "等待的"
  },
  "warm": {
    "ipa": "wɔːm",
    "cn": "温暖的"
  },
  "wet": {
    "ipa": "wɛt",
    "cn": "湿的"
  },
  "wide": {
    "ipa": "waɪd",
    "cn": "宽的"
  },
  "wise": {
    "ipa": "waɪz",
    "cn": "明智的"
  },
  "yellow": {
    "ipa": "ˈjɛl.əʊ",
    "cn": "黄色的"
  },
  "young": {
    "ipa": "jʌŋ",
    "cn": "年轻的"
  },
  "awake": {
    "ipa": "əˈweɪk",
    "cn": "醒着的"
  },
  "bad": {
    "ipa": "bæd",
    "cn": "差的"
  },
  "bent": {
    "ipa": "bɛnt",
    "cn": "弯曲的"
  },
  "bitter": {
    "ipa": "ˈbɪtə",
    "cn": "苦的"
  },
  "blue": {
    "ipa": "bluː",
    "cn": "蓝色的"
  },
  "certain": {
    "ipa": "ˈsɝtn̩",
    "cn": "确定的"
  },
  "cold": {
    "ipa": "kɔʊld",
    "cn": "冷的"
  },
  "complete": {
    "ipa": "kəmˈpliːt",
    "cn": "完整的"
  },
  "cruel": {
    "ipa": "kɹuː(ə)l",
    "cn": "残忍的"
  },
  "dark": {
    "ipa": "dɑːk",
    "cn": "黑暗的"
  },
  "dead": {
    "ipa": "diːd",
    "cn": "死的"
  },
  "dear": {
    "ipa": "dɪə",
    "cn": "亲爱的"
  },
  "delicate": {
    "ipa": "ˈdɛlɪkət",
    "cn": "精细的"
  },
  "different": {
    "ipa": "ˈdɪf.(ə)ɹ.ənt",
    "cn": "不同的"
  },
  "dog": {
    "ipa": "dɒɡ",
    "cn": "狗"
  },
  "be": {
    "cn": "是"
  },
  "have": {
    "cn": "有"
  },
  "at": {
    "cn": "在"
  },
  "with": {
    "cn": "与"
  },
  "as": {
    "cn": "如同"
  },
  "for": {
    "cn": "对于"
  },
  "every": {
    "cn": "每个"
  },
  "i": {
    "cn": "我"
  },
  "he": {
    "cn": "他"
  },
  "you": {
    "cn": "你"
  },
  "who": {
    "cn": "谁"
  },
  "and": {
    "cn": "和"
  },
  "because": {
    "cn": "因为"
  },
  "but": {
    "cn": "但是"
  },
  "or": {
    "cn": "或者"
  },
  "if": {
    "cn": "如果"
  },
  "though": {
    "cn": "虽然"
  },
  "while": {
    "cn": "当"
  },
  "how": {
    "cn": "如何"
  },
  "when": {
    "cn": "什么时候"
  },
  "where": {
    "cn": "在哪里"
  },
  "why": {
    "cn": "为什么"
  },
  "again": {
    "cn": "再次"
  },
  "ever": {
    "cn": "曾经"
  },
  "far": {
    "cn": "远"
  },
  "forward": {
    "cn": "向前"
  },
  "here": {
    "cn": "这里"
  },
  "near": {
    "cn": "附近"
  },
  "now": {
    "cn": "现在"
  },
  "out": {
    "cn": "外面"
  },
  "still": {
    "cn": "仍然"
  },
  "then": {
    "cn": "然后"
  },
  "there": {
    "cn": "那里"
  },
  "together": {
    "cn": "在一起"
  },
  "well": {
    "cn": "好"
  },
  "almost": {
    "cn": "几乎"
  },
  "enough": {
    "cn": "足够"
  },
  "cloth": {
    "cn": "布"
  },
  "coal": {
    "cn": "煤炭"
  },
  "colour": {
    "cn": "颜色"
  },
  "comfort": {
    "cn": "舒适"
  },
  "committee": {
    "cn": "委员会"
  },
  "company": {
    "cn": "公司"
  },
  "comparison": {
    "cn": "比较"
  },
  "competition": {
    "cn": "竞赛"
  },
  "condition": {
    "cn": "状况"
  },
  "connection": {
    "cn": "联系"
  },
  "control": {
    "cn": "控制"
  },
  "cook": {
    "cn": "厨师"
  },
  "copper": {
    "cn": "铜"
  },
  "copy": {
    "cn": "复制"
  },
  "cork": {
    "cn": "软木"
  },
  "cotton": {
    "cn": "棉布"
  },
  "cough": {
    "cn": "咳嗽"
  },
  "country": {
    "cn": "国家"
  },
  "cover": {
    "cn": "封面"
  },
  "crack": {
    "cn": "裂缝"
  },
  "credit": {
    "cn": "信用"
  },
  "crime": {
    "cn": "罪案"
  },
  "crush": {
    "cn": "压碎"
  },
  "cry": {
    "cn": "哭"
  },
  "current": {
    "cn": "当前的"
  },
  "curve": {
    "cn": "曲线"
  },
  "damage": {
    "cn": "损害"
  },
  "danger": {
    "cn": "危险"
  },
  "daughter": {
    "cn": "女儿"
  },
  "error": {
    "cn": "错误"
  },
  "increase": {
    "cn": "增加"
  },
  "look": {
    "cn": "看"
  },
  "meeting": {
    "cn": "会议"
  },
  "memory": {
    "cn": "记忆"
  },
  "metal": {
    "cn": "金属"
  },
  "middle": {
    "cn": "中间"
  },
  "milk": {
    "cn": "牛奶"
  },
  "mind": {
    "cn": "头脑"
  },
  "mine": {
    "cn": "矿"
  },
  "minute": {
    "cn": "分钟"
  },
  "mist": {
    "cn": "薄雾"
  },
  "money": {
    "cn": "钱"
  },
  "month": {
    "cn": "月"
  },
  "morning": {
    "cn": "早晨"
  },
  "mother": {
    "cn": "母亲"
  },
  "motion": {
    "cn": "运动"
  },
  "mountain": {
    "cn": "山"
  },
  "move": {
    "cn": "移动"
  },
  "music": {
    "cn": "音乐"
  },
  "name": {
    "cn": "姓名"
  },
  "nation": {
    "cn": "国家"
  },
  "need": {
    "cn": "需要"
  },
  "news": {
    "cn": "消息"
  },
  "night": {
    "cn": "夜晚"
  },
  "noise": {
    "cn": "噪音"
  },
  "note": {
    "cn": "笔记"
  },
  "number": {
    "cn": "数字"
  },
  "observation": {
    "cn": "观察"
  },
  "offer": {
    "cn": "提供"
  },
  "oil": {
    "cn": "油"
  },
  "operation": {
    "cn": "手术"
  },
  "opinion": {
    "cn": "观点"
  },
  "scale": {
    "cn": "规模"
  },
  "science": {
    "cn": "科学"
  },
  "sea": {
    "cn": "海"
  },
  "seat": {
    "cn": "座位"
  },
  "secretary": {
    "cn": "秘书"
  },
  "selection": {
    "cn": "选择"
  },
  "self": {
    "cn": "自己"
  },
  "sense": {
    "cn": "感觉"
  },
  "servant": {
    "cn": "仆人"
  },
  "sex": {
    "cn": "性别"
  },
  "shade": {
    "cn": "阴影"
  },
  "shake": {
    "cn": "摇"
  },
  "shame": {
    "cn": "耻辱"
  },
  "shock": {
    "cn": "震惊"
  },
  "side": {
    "cn": "边"
  },
  "sign": {
    "cn": "符号"
  },
  "silk": {
    "cn": "丝绸"
  },
  "silver": {
    "cn": "银"
  },
  "sister": {
    "cn": "姐姐"
  },
  "size": {
    "cn": "尺寸"
  },
  "sky": {
    "cn": "天空"
  },
  "sleep": {
    "cn": "睡觉"
  },
  "slip": {
    "cn": "滑"
  },
  "slope": {
    "cn": "坡"
  },
  "smash": {
    "cn": "粉碎"
  },
  "smell": {
    "cn": "闻"
  },
  "smile": {
    "cn": "微笑"
  },
  "smoke": {
    "cn": "抽烟"
  },
  "sneeze": {
    "cn": "喷嚏"
  },
  "snow": {
    "cn": "雪"
  },
  "touch": {
    "cn": "触碰"
  },
  "transport": {
    "cn": "运输"
  },
  "use": {
    "cn": "使用"
  },
  "army": {
    "cn": "军队"
  },
  "baby": {
    "cn": "婴儿"
  },
  "bag": {
    "cn": "袋子"
  },
  "ball": {
    "cn": "球"
  },
  "band": {
    "cn": "乐队"
  },
  "basin": {
    "cn": "盆地"
  },
  "basket": {
    "cn": "篮子"
  },
  "bath": {
    "cn": "洗澡"
  },
  "bed": {
    "cn": "床"
  },
  "bee": {
    "cn": "蜜蜂"
  },
  "bell": {
    "cn": "铃铛"
  },
  "berry": {
    "cn": "浆果"
  },
  "bird": {
    "cn": "鸟"
  },
  "blade": {
    "cn": "刀刃"
  },
  "board": {
    "cn": "木板"
  },
  "boat": {
    "cn": "船"
  },
  "bone": {
    "cn": "骨"
  },
  "book": {
    "cn": "书"
  },
  "cushion": {
    "cn": "软垫"
  },
  "door": {
    "cn": "门"
  },
  "drain": {
    "cn": "流走"
  },
  "drawer": {
    "cn": "抽屉"
  },
  "dress": {
    "cn": "裙子"
  },
  "drop": {
    "cn": "降低"
  },
  "ear": {
    "cn": "耳朵"
  },
  "egg": {
    "cn": "蛋"
  },
  "engine": {
    "cn": "引擎"
  },
  "eye": {
    "cn": "眼睛"
  },
  "face": {
    "cn": "脸"
  },
  "farm": {
    "cn": "农场"
  },
  "knife": {
    "cn": "刀"
  },
  "knot": {
    "cn": "结"
  },
  "leaf": {
    "cn": "叶子"
  },
  "leg": {
    "cn": "腿"
  },
  "library": {
    "cn": "图书馆"
  },
  "line": {
    "cn": "线"
  },
  "lip": {
    "cn": "唇"
  },
  "lock": {
    "cn": "锁"
  },
  "map": {
    "cn": "地图"
  },
  "match": {
    "cn": "匹配"
  },
  "monkey": {
    "cn": "猴"
  },
  "moon": {
    "cn": "月亮"
  },
  "mouth": {
    "cn": "嘴"
  },
  "muscle": {
    "cn": "肌肉"
  },
  "nail": {
    "cn": "指甲"
  },
  "neck": {
    "cn": "脖子"
  },
  "net": {
    "cn": "网"
  },
  "sock": {
    "cn": "短袜"
  },
  "spade": {
    "cn": "铲"
  },
  "sponge": {
    "cn": "海绵"
  },
  "spoon": {
    "cn": "勺子"
  },
  "spring": {
    "cn": "春天"
  },
  "square": {
    "cn": "正方形"
  },
  "stamp": {
    "cn": "邮票"
  },
  "star": {
    "cn": "星星"
  },
  "station": {
    "cn": "车站"
  },
  "stem": {
    "cn": "干"
  },
  "stick": {
    "cn": "戳"
  },
  "stocking": {
    "cn": "袜"
  },
  "stomach": {
    "cn": "胃"
  },
  "store": {
    "cn": "店铺"
  },
  "angry": {
    "cn": "生气的"
  },
  "automatic": {
    "cn": "自动的"
  },
  "beautiful": {
    "cn": "美丽的"
  },
  "black": {
    "cn": "黑色的"
  },
  "boiling": {
    "cn": "沸腾的"
  },
  "bright": {
    "cn": "明亮的"
  },
  "broken": {
    "cn": "破碎的"
  },
  "brown": {
    "cn": "棕色的"
  },
  "cheap": {
    "cn": "便宜的"
  },
  "chemical": {
    "cn": "化学的"
  },
  "chief": {
    "cn": "主要的"
  },
  "clean": {
    "cn": "干净的"
  },
  "clear": {
    "cn": "清晰的"
  },
  "common": {
    "cn": "常见的"
  },
  "complex": {
    "cn": "复杂的"
  },
  "conscious": {
    "cn": "有意识的"
  },
  "cut": {
    "cn": "切割的"
  },
  "deep": {
    "cn": "深的"
  },
  "dependent": {
    "cn": "依赖的"
  },
  "early": {
    "cn": "早的"
  },
  "quiet": {
    "cn": "安静的"
  },
  "ready": {
    "cn": "准备好的"
  },
  "red": {
    "cn": "红色的"
  },
  "regular": {
    "cn": "规则的"
  },
  "responsible": {
    "cn": "负责任的"
  },
  "right": {
    "cn": "正确的"
  },
  "round": {
    "cn": "圆的"
  },
  "same": {
    "cn": "相同的"
  },
  "second": {
    "cn": "第二的"
  },
  "separate": {
    "cn": "分离的"
  },
  "serious": {
    "cn": "严肃的"
  },
  "tight": {
    "cn": "紧的"
  },
  "dirty": {
    "cn": "脏的"
  },
  "dry": {
    "cn": "干的"
  },
  "false": {
    "cn": "错误的"
  },
  "feeble": {
    "cn": "无力的"
  },
  "female": {
    "cn": "女性的"
  },
  "foolish": {
    "cn": "愚蠢的"
  },
  "future": {
    "cn": "未来的"
  },
  "green": {
    "cn": "绿色的"
  },
  "ill": {
    "cn": "生病的"
  },
  "last": {
    "cn": "最后的"
  },
  "late": {
    "cn": "晚的"
  },
  "left": {
    "cn": "左边的"
  },
  "loose": {
    "cn": "松的"
  },
  "loud": {
    "cn": "大声的"
  },
  "low": {
    "cn": "低的"
  },
  "mixed": {
    "cn": "混合的"
  }
}